avesterra/__init__.py
avesterra/annotation.py
avesterra/api.py
avesterra/aspects.py
avesterra/attributions.py
avesterra/av_log.py
avesterra/avesterra.py
avesterra/avial.py
avesterra/avial_model.py
avesterra/boost.py
avesterra/collections.py
avesterra/columns.py
avesterra/facets.py
avesterra/factors.py
avesterra/facts.py
avesterra/features.py
avesterra/fields.py
avesterra/files.py
avesterra/firewall.py
avesterra/folders.py
avesterra/frames.py
avesterra/generals.py
avesterra/hgtp.py
avesterra/items.py
avesterra/objects.py
avesterra/outlets.py
avesterra/parameters.py
avesterra/predefined.py
avesterra/properties.py
avesterra/registries.py
avesterra/routing.py
avesterra/rows.py
avesterra/spaces.py
avesterra/tables.py
avesterra/taxonomy.py
avesterra/tokens.py
avesterra/traits.py
avesterra/trash.py
avesterra/tunnels.py
orchestra/__init__.py
orchestra/_hns.py
orchestra/_log_publisher.py
orchestra/adapter.py
orchestra/adapter_interface.py
orchestra/env.py
orchestra/mount.py
orchestra/orchestra_adapter.py
orchestra/sysmon.py
orchestra/utils.py
orchestra_toolkit-25.4.2.dist-info/METADATA
orchestra_toolkit-25.4.2.dist-info/WHEEL
orchestra_toolkit-25.4.2.dist-info/top_level.txt
orchestra_toolkit-25.4.2.dist-info/RECORD
