Metadata-Version: 2.1
Name: orchestra-toolkit
Version: 25.4.2
Summary: A python client to interract with Orchestra systems
Author: LEDR Technologies inc.
Author-email: support@ledr.io
Classifier: Programming Language :: Python :: 3.10
Classifier: Programming Language :: Python :: 3.11
Classifier: Programming Language :: Python :: 3.12
Classifier: Intended Audience :: Developers
Classifier: Topic :: Internet
Classifier: License :: OSI Approved :: GNU Lesser General Public License v3 or later (LGPLv3+)
Classifier: Development Status :: 4 - Beta
Requires-Python: >=3.10
Requires-Dist: tabulate
Requires-Dist: treelib
Requires-Dist: typing-extensions
